cnb_tools/__init__.py
cnb_tools/__main__.py
cnb_tools/commands/submission_cli.py
cnb_tools/main_cli.py
cnb_tools/modules/annotation.py
cnb_tools/modules/auth.py
cnb_tools/modules/exceptions.py
cnb_tools/modules/participant.py
cnb_tools/modules/queue.py
cnb_tools/modules/submission.py
cnb_tools/validation_toolkit.py
cnb_tools-0.3.2.dist-info/LICENSE
cnb_tools-0.3.2.dist-info/METADATA
cnb_tools-0.3.2.dist-info/WHEEL
cnb_tools-0.3.2.dist-info/entry_points.txt
cnb_tools-0.3.2.dist-info/RECORD
