Metadata-Version: 2.1
Name: cnb-tools
Version: 0.3.2
Summary: Convenience tools/functions for challenges and benchmarking on Synapse.org
Home-page: https://github.com/Sage-Bionetworks-Challenges/cnb-tools
License: Apache-2.0
Author: Sage CNB Team
Author-email: cnb@sagebase.org
Maintainer: Verena Chung
Maintainer-email: verena.chung@sagebase.org
Requires-Python: >=3.9,<4.0
Classifier: Development Status :: 3 - Alpha
Classifier: Intended Audience :: Developers
Classifier: Intended Audience :: Science/Research
Classifier: License :: OSI Approved :: Apache Software License
Classifier: Natural Language :: English
Classifier: Programming Language :: Python
Classifier: Programming Language :: Python :: 3
Classifier: Programming Language :: Python :: 3.9
Classifier: Programming Language :: Python :: 3.10
Classifier: Programming Language :: Python :: 3.11
Classifier: Programming Language :: Python :: 3.12
Classifier: Topic :: Scientific/Engineering
Classifier: Topic :: Scientific/Engineering :: Bio-Informatics
Classifier: Topic :: Software Development :: Libraries :: Python Modules
Requires-Dist: synapseclient (>=4.2.0,<5.0.0)
Requires-Dist: typer[all] (>=0.9.0,<0.10.0)
Project-URL: Bug Tracker, https://github.com/Sage-Bionetworks-Challenges/cnb-tools/issues
Project-URL: Documentation, https://sage-bionetworks-challenges.github.io/cnb-tools
Project-URL: Repository, https://github.com/Sage-Bionetworks-Challenges/cnb-tools
